README.txt
fetch.py
setup.py
fetch.egg-info/PKG-INFO
fetch.egg-info/SOURCES.txt
fetch.egg-info/dependency_links.txt
fetch.egg-info/entry_points.txt
fetch.egg-info/not-zip-safe
fetch.egg-info/top_level.txt