Metadata-Version: 1.0
Name: fetch
Version: 0.0
Summary: fetch stuff from the interwebs
Home-page: http://k0s.org/mozilla/fetch
Author: Jeff Hammel
Author-email: jhammel@mozilla.com
License: MPL
Platform: UNKNOWN
